{
    "craft_plank": {
        "category": "player",
        "subtitle": "natural-progression.subtitle.craft_plank",
        "sounds": [
            "natural-progression:craft_plank_1",
            "natural-progression:craft_plank_2"
        ]
    },
    "craft_other": {
        "category": "player",
        "subtitle": "natural-progression.subtitle.craft_other",
        "sounds": [
            "natural-progression:craft_other_1",
            "natural-progression:craft_other_2",
            "natural-progression:craft_other_3"
        ]
    }
}